file_wizard/__init__.py
file_wizard/file_manager.py
file_wizard/logger.py
file_wizard-1.0.1.dist-info/LICENSE
file_wizard-1.0.1.dist-info/METADATA
file_wizard-1.0.1.dist-info/WHEEL
file_wizard-1.0.1.dist-info/top_level.txt
file_wizard-1.0.1.dist-info/RECORD
