Metadata-Version: 2.1
Name: file-wizard
Version: 1.0.1
Summary: A basic file handler for python tools
Home-page: https://gitlab.com/file-wizard/file-wizard
Author: S Krishna Bhat, Pankaj Kumar G
Author-email: ccrc@fisat.ac.in
License: UNKNOWN
Platform: UNKNOWN
Classifier: Programming Language :: Python :: 3
Classifier: License :: OSI Approved :: BSD License
Classifier: Operating System :: OS Independent
Requires-Python: >=3.6
Requires-Dist: shutils
